swiss_qr_bill/__init__.py
swiss_qr_bill/canvas/__init__.py
swiss_qr_bill/canvas/canvas_base.py
swiss_qr_bill/canvas/char_width_data.py
swiss_qr_bill/canvas/fontmetrics.py
swiss_qr_bill/canvas/svg_canvas.py
swiss_qr_bill/generator/__init__.py
swiss_qr_bill/generator/address.py
swiss_qr_bill/generator/alternative_scheme.py
swiss_qr_bill/generator/bill.py
swiss_qr_bill/generator/bill_format.py
swiss_qr_bill/generator/bill_layout.py
swiss_qr_bill/generator/enums.py
swiss_qr_bill/generator/multi_lingual_text.py
swiss_qr_bill/generator/payments.py
swiss_qr_bill/generator/qr_bill.py
swiss_qr_bill/generator/qr_code.py
swiss_qr_bill/generator/qr_code_text.py
swiss_qr_bill/validator/__init__.py
swiss_qr_bill/validator/helpers.py
swiss_qr_bill/validator/validator.py
swiss_qr_bill-0.0.31.dist-info/licenses/LICENSE
swiss_qr_bill-0.0.31.dist-info/METADATA
swiss_qr_bill-0.0.31.dist-info/WHEEL
swiss_qr_bill-0.0.31.dist-info/top_level.txt
swiss_qr_bill-0.0.31.dist-info/RECORD
